pyproject.toml
ThalamusDB.egg-info/PKG-INFO
ThalamusDB.egg-info/SOURCES.txt
ThalamusDB.egg-info/dependency_links.txt
ThalamusDB.egg-info/entry_points.txt
ThalamusDB.egg-info/requires.txt
ThalamusDB.egg-info/top_level.txt
tdb/__init__.py
tdb/console.py
tdb/data/__init__.py
tdb/data/relational.py
tdb/execution/__init__.py
tdb/execution/constraints.py
tdb/execution/counters.py
tdb/execution/engine.py
tdb/execution/results.py
tdb/operators/__init__.py
tdb/operators/semantic_filter.py
tdb/operators/semantic_join.py
tdb/operators/semantic_operator.py
tdb/queries/__init__.py
tdb/queries/query.py
tdb/queries/rewriter.py
tdb/ui/__init__.py
tdb/ui/util.py
test/test_util.py
thalamusdb.egg-info/PKG-INFO
thalamusdb.egg-info/SOURCES.txt
thalamusdb.egg-info/dependency_links.txt
thalamusdb.egg-info/entry_points.txt
thalamusdb.egg-info/requires.txt
thalamusdb.egg-info/top_level.txt