Metadata-Version: 2.4
Name: ThalamusDB
Version: 0.1.13
Summary: ThalamusDB: Semantic Query Processing on Multimodal Data
Author: Immanuel Trummer, Saehan Jo
License-Expression: MIT
Keywords: semantic query processing,multimodal data,large language models,approximate query processing
Requires-Python: >=3.12
Requires-Dist: duckdb==1.3.2
Requires-Dist: pandas==2.3.1
Requires-Dist: sqlglot==27.0.0
Requires-Dist: rich==13.9.4
Requires-Dist: pytest==8.4.1
Requires-Dist: pytest-mock==3.14
Requires-Dist: litellm==1.75.8
Requires-Dist: prompt_toolkit==3.0.51
